baselines/__init__.py
baselines/ppo/__init__.py
baselines/ppo/ppo_memtasks.py
baselines/ppo/ppo_memtasks_lstm.py
dataset_collectors/__init__.py
dataset_collectors/get_dataset_collectors_ckpt.py
dataset_collectors/get_mikasa_robo_datasets.py
dataset_collectors/parallel_dataset_collection_manager.py
dataset_collectors/parallel_training_manager.py
mikasa_robo/__init__.py
mikasa_robo/bunch_of_colors.py
mikasa_robo/chain_of_colors.py
mikasa_robo/intercept.py
mikasa_robo/intercept_grab.py
mikasa_robo/remember_color.py
mikasa_robo/remember_shape.py
mikasa_robo/remember_shape_and_color.py
mikasa_robo/rotate_lenient.py
mikasa_robo/rotate_strict.py
mikasa_robo/seq_of_colors.py
mikasa_robo/shell_game_pick.py
mikasa_robo/shell_game_push.py
mikasa_robo/shell_game_touch.py
mikasa_robo/take_it_back.py
utils/__init__.py
utils/shapes.py
utils/wrappers.py
mikasa_robo-0.0.1.dist-info/LICENSE
mikasa_robo-0.0.1.dist-info/METADATA
mikasa_robo-0.0.1.dist-info/WHEEL
mikasa_robo-0.0.1.dist-info/top_level.txt
mikasa_robo-0.0.1.dist-info/RECORD
