Metadata-Version: 2.1
Name: mikasa_robo
Version: 0.0.1
Summary: Gym-like memory-intensive environmtnts for robotic tabletop manipulation
Home-page: https://github.com/CognitiveAISystems/MIKASA-Robo
Author: Egor Cherepanov
Author-email: cherepanovegor2018@gmail.com
Classifier: Programming Language :: Python :: 3
Classifier: License :: OSI Approved :: MIT License
Classifier: Operating System :: OS Independent
Requires-Python: >=3.9
License-File: LICENSE
Requires-Dist: gymnasium==0.29.1
Requires-Dist: mani_skill==3.0.0b15
Requires-Dist: matplotlib==3.9.2
Requires-Dist: numpy==1.23.5
Requires-Dist: torch==2.2.1
Requires-Dist: wandb==0.18.5
Requires-Dist: tensorboard==2.18.0
Requires-Dist: colorama==0.4.6
Requires-Dist: tqdm
Requires-Dist: pandas
Requires-Dist: ipywidgets
Requires-Dist: opencv-python==4.10.0.84
Requires-Dist: gputil
Requires-Dist: psutil
